setup.cfg
setup.py
commandline/__init__.py
commandline/commandline.py
commandline/inspect_convenience.py
commandline/test.py
commandline.egg-info/PKG-INFO
commandline.egg-info/SOURCES.txt
commandline.egg-info/dependency_links.txt
commandline.egg-info/entry_points.txt
commandline.egg-info/top_level.txt
commandline.egg-info/zip-safe