Metadata-Version: 1.0
Name: commandline
Version: 0.1.2dev
Summary: Exposes your APIs to the command line.
Home-page: UNKNOWN
Author: David Laban
Author-email: alsuren@gmail.com
License: BSD
Keywords: command line commandline script
Platform: UNKNOWN
